aws3lib/aws.py
aws3lib/example.py
aws3lib/exceptions.py
aws3lib-1.0.5.dist-info/METADATA
aws3lib-1.0.5.dist-info/WHEEL
aws3lib-1.0.5.dist-info/top_level.txt
aws3lib-1.0.5.dist-info/RECORD
